nzmath/__init__.py
nzmath/algfield.py
nzmath/algorithm.py
nzmath/all.py
nzmath/arith1.py
nzmath/arygcd.py
nzmath/bigrandom.py
nzmath/bigrange.py
nzmath/combinatorial.py
nzmath/compatibility.py
nzmath/config.py
nzmath/cubic_root.py
nzmath/cyclotomic.py
nzmath/ecpp.py
nzmath/elliptic.py
nzmath/equation.py
nzmath/finitefield.py
nzmath/gcd.py
nzmath/group.py
nzmath/imaginary.py
nzmath/intresidue.py
nzmath/lattice.py
nzmath/matrix.py
nzmath/module.py
nzmath/multiplicative.py
nzmath/permute.py
nzmath/plugins.py
nzmath/prime.py
nzmath/prime_decomp.py
nzmath/quad.py
nzmath/rational.py
nzmath/real.py
nzmath/residue.py
nzmath/ring.py
nzmath/round2.py
nzmath/sequence.py
nzmath/squarefree.py
nzmath/vector.py
nzmath/config/nzmathconf.py
nzmath/data/discriminant.csv
nzmath/data/primitiveRootPW_.csv
nzmath/data/primitiveRoots.csv
nzmath/factor/__init__.py
nzmath/factor/ecm.py
nzmath/factor/find.py
nzmath/factor/methods.py
nzmath/factor/misc.py
nzmath/factor/mpqs.py
nzmath/factor/util.py
nzmath/manual/en/nzmath_doc.pdf
nzmath/manual/ja/nzmath_doc.pdf
nzmath/plugin/__init__.py
nzmath/plugin/math/__init__.py
nzmath/plugin/math/_mpmath.py
nzmath/plugin/math/default.py
nzmath/poly/__init__.py
nzmath/poly/array.py
nzmath/poly/factor.py
nzmath/poly/formalsum.py
nzmath/poly/groebner.py
nzmath/poly/hensel.py
nzmath/poly/multiutil.py
nzmath/poly/multivar.py
nzmath/poly/ratfunc.py
nzmath/poly/ring.py
nzmath/poly/termorder.py
nzmath/poly/uniutil.py
nzmath/poly/univar.py
nzmath-3.0.3.dist-info/licenses/LICENSE.txt
nzmath-3.0.3.dist-info/METADATA
nzmath-3.0.3.dist-info/WHEEL
nzmath-3.0.3.dist-info/top_level.txt
nzmath-3.0.3.dist-info/RECORD
