Metadata-Version: 2.4
Name: nzmath
Version: 3.0.3
Summary: Python calculator on number theory
Author-email: NZMATH development group <nzmath-mail@lists.sourceforge.net>
Project-URL: Homepage, https://nzmath.sourceforge.io/
Project-URL: Documentation, https://nzmath.sourceforge.io/tutorial.html
Project-URL: User Manual, https://nzmath.sourceforge.io/nzmath_doc.pdf
Project-URL: Repository, https://sourceforge.net/p/nzmath/code/
Classifier: Development Status :: 5 - Production/Stable
Classifier: Programming Language :: Python :: 3
Classifier: License :: OSI Approved :: BSD License
Classifier: Operating System :: OS Independent
Classifier: Topic :: Scientific/Engineering :: Mathematics
Requires-Python: >=3.9
License-File: LICENSE.txt
Dynamic: license-file
